{
  "scraped_at": "2026-06-30T20:03:25.474673+00:00",
  "source": "https://sis.pesrp.edu.pk",
  "summary": {
    "total_districts": 40,
    "total_schools": 38150,
    "total_students": 10467126,
    "total_boys": 5010516,
    "total_girls": 5455732
  },
  "districts": [
    {
      "district_id": "1",
      "district": "ATTOCK",
      "slug": "attock",
      "file": "data/attock.json",
      "total_schools": 850,
      "total_students": 221326,
      "total_boys": 101284,
      "total_girls": 120035,
      "scraped_at": "2026-06-30T20:03:25.474673+00:00"
    },
    {
      "district_id": "2",
      "district": "BAHAWALNAGAR",
      "slug": "bahawalnagar",
      "file": "data/bahawalnagar.json",
      "total_schools": 1590,
      "total_students": 347306,
      "total_boys": 171256,
      "total_girls": 176027,
      "scraped_at": "2026-06-30T20:03:25.474673+00:00"
    },
    {
      "district_id": "3",
      "district": "BAHAWALPUR",
      "slug": "bahawalpur",
      "file": "data/bahawalpur.json",
      "total_schools": 1305,
      "total_students": 299669,
      "total_boys": 146095,
      "total_girls": 153558,
      "scraped_at": "2026-06-30T20:03:25.474673+00:00"
    },
    {
      "district_id": "4",
      "district": "BHAKKAR",
      "slug": "bhakkar",
      "file": "data/bhakkar.json",
      "total_schools": 967,
      "total_students": 222353,
      "total_boys": 119987,
      "total_girls": 102346,
      "scraped_at": "2026-06-30T20:03:25.474673+00:00"
    },
    {
      "district_id": "5",
      "district": "CHAKWAL",
      "slug": "chakwal",
      "file": "data/chakwal.json",
      "total_schools": 533,
      "total_students": 94926,
      "total_boys": 43472,
      "total_girls": 51448,
      "scraped_at": "2026-06-30T20:03:25.474673+00:00"
    },
    {
      "district_id": "6",
      "district": "CHINIOT",
      "slug": "chiniot",
      "file": "data/chiniot.json",
      "total_schools": 551,
      "total_students": 164567,
      "total_boys": 84491,
      "total_girls": 80070,
      "scraped_at": "2026-06-30T20:03:25.474673+00:00"
    },
    {
      "district_id": "7",
      "district": "D.G. KHAN",
      "slug": "d_g_khan",
      "file": "data/d_g_khan.json",
      "total_schools": 1217,
      "total_students": 276336,
      "total_boys": 142408,
      "total_girls": 133904,
      "scraped_at": "2026-06-30T20:03:25.474673+00:00"
    },
    {
      "district_id": "8",
      "district": "FAISALABAD",
      "slug": "faisalabad",
      "file": "data/faisalabad.json",
      "total_schools": 1933,
      "total_students": 728192,
      "total_boys": 330244,
      "total_girls": 397865,
      "scraped_at": "2026-06-30T20:03:25.474673+00:00"
    },
    {
      "district_id": "9",
      "district": "GUJRANWALA",
      "slug": "gujranwala",
      "file": "data/gujranwala.json",
      "total_schools": 884,
      "total_students": 296587,
      "total_boys": 131121,
      "total_girls": 165432,
      "scraped_at": "2026-06-30T20:03:25.474673+00:00"
    },
    {
      "district_id": "10",
      "district": "GUJRAT",
      "slug": "gujrat",
      "file": "data/gujrat.json",
      "total_schools": 1067,
      "total_students": 291191,
      "total_boys": 128778,
      "total_girls": 162392,
      "scraped_at": "2026-06-30T20:03:25.474673+00:00"
    },
    {
      "district_id": "11",
      "district": "HAFIZABAD",
      "slug": "hafizabad",
      "file": "data/hafizabad.json",
      "total_schools": 533,
      "total_students": 131023,
      "total_boys": 63158,
      "total_girls": 67856,
      "scraped_at": "2026-06-30T20:03:25.474673+00:00"
    },
    {
      "district_id": "12",
      "district": "JHANG",
      "slug": "jhang",
      "file": "data/jhang.json",
      "total_schools": 1256,
      "total_students": 324049,
      "total_boys": 167547,
      "total_girls": 156487,
      "scraped_at": "2026-06-30T20:03:25.474673+00:00"
    },
    {
      "district_id": "13",
      "district": "JHELUM",
      "slug": "jhelum",
      "file": "data/jhelum.json",
      "total_schools": 556,
      "total_students": 132924,
      "total_boys": 59975,
      "total_girls": 72941,
      "scraped_at": "2026-06-30T20:03:25.474673+00:00"
    },
    {
      "district_id": "14",
      "district": "KASUR",
      "slug": "kasur",
      "file": "data/kasur.json",
      "total_schools": 1111,
      "total_students": 330971,
      "total_boys": 154125,
      "total_girls": 176823,
      "scraped_at": "2026-06-30T20:03:25.474673+00:00"
    },
    {
      "district_id": "15",
      "district": "KHANEWAL",
      "slug": "khanewal",
      "file": "data/khanewal.json",
      "total_schools": 1033,
      "total_students": 360585,
      "total_boys": 177197,
      "total_girls": 183358,
      "scraped_at": "2026-06-30T20:03:25.474673+00:00"
    },
    {
      "district_id": "16",
      "district": "KHUSHAB",
      "slug": "khushab",
      "file": "data/khushab.json",
      "total_schools": 664,
      "total_students": 141047,
      "total_boys": 73975,
      "total_girls": 67065,
      "scraped_at": "2026-06-30T20:03:25.474673+00:00"
    },
    {
      "district_id": "37",
      "district": "KOT ADU",
      "slug": "kot_adu",
      "file": "data/kot_adu.json",
      "total_schools": 585,
      "total_students": 122580,
      "total_boys": 64025,
      "total_girls": 58547,
      "scraped_at": "2026-06-30T20:03:25.474673+00:00"
    },
    {
      "district_id": "17",
      "district": "LAHORE",
      "slug": "lahore",
      "file": "data/lahore.json",
      "total_schools": 1028,
      "total_students": 592460,
      "total_boys": 251787,
      "total_girls": 340579,
      "scraped_at": "2026-06-30T20:03:25.474673+00:00"
    },
    {
      "district_id": "18",
      "district": "LAYYAH",
      "slug": "layyah",
      "file": "data/layyah.json",
      "total_schools": 1223,
      "total_students": 264066,
      "total_boys": 132566,
      "total_girls": 131478,
      "scraped_at": "2026-06-30T20:03:25.474673+00:00"
    },
    {
      "district_id": "19",
      "district": "LODHRAN",
      "slug": "lodhran",
      "file": "data/lodhran.json",
      "total_schools": 632,
      "total_students": 148883,
      "total_boys": 76297,
      "total_girls": 72577,
      "scraped_at": "2026-06-30T20:03:25.474673+00:00"
    },
    {
      "district_id": "20",
      "district": "MANDI BAHA UD DIN",
      "slug": "mandi_baha_ud_din",
      "file": "data/mandi_baha_ud_din.json",
      "total_schools": 661,
      "total_students": 180054,
      "total_boys": 81989,
      "total_girls": 98044,
      "scraped_at": "2026-06-30T20:03:25.474673+00:00"
    },
    {
      "district_id": "21",
      "district": "MIANWALI",
      "slug": "mianwali",
      "file": "data/mianwali.json",
      "total_schools": 990,
      "total_students": 221453,
      "total_boys": 119917,
      "total_girls": 101524,
      "scraped_at": "2026-06-30T20:03:25.474673+00:00"
    },
    {
      "district_id": "22",
      "district": "MULTAN",
      "slug": "multan",
      "file": "data/multan.json",
      "total_schools": 1097,
      "total_students": 346621,
      "total_boys": 168246,
      "total_girls": 178346,
      "scraped_at": "2026-06-30T20:03:25.474673+00:00"
    },
    {
      "district_id": "38",
      "district": "MURREE",
      "slug": "murree",
      "file": "data/murree.json",
      "total_schools": 267,
      "total_students": 38218,
      "total_boys": 18166,
      "total_girls": 20050,
      "scraped_at": "2026-06-30T20:03:25.474673+00:00"
    },
    {
      "district_id": "23",
      "district": "MUZAFFARGARH",
      "slug": "muzaffargarh",
      "file": "data/muzaffargarh.json",
      "total_schools": 871,
      "total_students": 218575,
      "total_boys": 116316,
      "total_girls": 102248,
      "scraped_at": "2026-06-30T20:03:25.474673+00:00"
    },
    {
      "district_id": "24",
      "district": "NANKANA SAHIB",
      "slug": "nankana_sahib",
      "file": "data/nankana_sahib.json",
      "total_schools": 621,
      "total_students": 164876,
      "total_boys": 80768,
      "total_girls": 84097,
      "scraped_at": "2026-06-30T20:03:25.474673+00:00"
    },
    {
      "district_id": "25",
      "district": "NAROWAL",
      "slug": "narowal",
      "file": "data/narowal.json",
      "total_schools": 956,
      "total_students": 192279,
      "total_boys": 88996,
      "total_girls": 103264,
      "scraped_at": "2026-06-30T20:03:25.474673+00:00"
    },
    {
      "district_id": "26",
      "district": "OKARA",
      "slug": "okara",
      "file": "data/okara.json",
      "total_schools": 1112,
      "total_students": 308576,
      "total_boys": 150019,
      "total_girls": 158510,
      "scraped_at": "2026-06-30T20:03:25.474673+00:00"
    },
    {
      "district_id": "27",
      "district": "PAKPATTAN",
      "slug": "pakpattan",
      "file": "data/pakpattan.json",
      "total_schools": 692,
      "total_students": 197289,
      "total_boys": 100660,
      "total_girls": 96613,
      "scraped_at": "2026-06-30T20:03:25.474673+00:00"
    },
    {
      "district_id": "28",
      "district": "RAHIMYAR KHAN",
      "slug": "rahimyar_khan",
      "file": "data/rahimyar_khan.json",
      "total_schools": 2093,
      "total_students": 529515,
      "total_boys": 272343,
      "total_girls": 257131,
      "scraped_at": "2026-06-30T20:03:25.474673+00:00"
    },
    {
      "district_id": "29",
      "district": "RAJANPUR",
      "slug": "rajanpur",
      "file": "data/rajanpur.json",
      "total_schools": 775,
      "total_students": 181161,
      "total_boys": 102019,
      "total_girls": 79129,
      "scraped_at": "2026-06-30T20:03:25.474673+00:00"
    },
    {
      "district_id": "30",
      "district": "RAWALPINDI",
      "slug": "rawalpindi",
      "file": "data/rawalpindi.json",
      "total_schools": 1178,
      "total_students": 320016,
      "total_boys": 134441,
      "total_girls": 185553,
      "scraped_at": "2026-06-30T20:03:25.474673+00:00"
    },
    {
      "district_id": "31",
      "district": "SAHIWAL",
      "slug": "sahiwal",
      "file": "data/sahiwal.json",
      "total_schools": 944,
      "total_students": 319807,
      "total_boys": 151091,
      "total_girls": 168691,
      "scraped_at": "2026-06-30T20:03:25.474673+00:00"
    },
    {
      "district_id": "32",
      "district": "SARGODHA",
      "slug": "sargodha",
      "file": "data/sargodha.json",
      "total_schools": 1455,
      "total_students": 392876,
      "total_boys": 178766,
      "total_girls": 214085,
      "scraped_at": "2026-06-30T20:03:25.474673+00:00"
    },
    {
      "district_id": "33",
      "district": "SHEIKHUPURA",
      "slug": "sheikhupura",
      "file": "data/sheikhupura.json",
      "total_schools": 910,
      "total_students": 290277,
      "total_boys": 131931,
      "total_girls": 158309,
      "scraped_at": "2026-06-30T20:03:25.474673+00:00"
    },
    {
      "district_id": "34",
      "district": "SIALKOT",
      "slug": "sialkot",
      "file": "data/sialkot.json",
      "total_schools": 1278,
      "total_students": 349637,
      "total_boys": 153252,
      "total_girls": 196351,
      "scraped_at": "2026-06-30T20:03:25.474673+00:00"
    },
    {
      "district_id": "35",
      "district": "T.T.SINGH",
      "slug": "t_t_singh",
      "file": "data/t_t_singh.json",
      "total_schools": 1024,
      "total_students": 296749,
      "total_boys": 137311,
      "total_girls": 159420,
      "scraped_at": "2026-06-30T20:03:25.474673+00:00"
    },
    {
      "district_id": "39",
      "district": "TALAGANG",
      "slug": "talagang",
      "file": "data/talagang.json",
      "total_schools": 294,
      "total_students": 57992,
      "total_boys": 27793,
      "total_girls": 30197,
      "scraped_at": "2026-06-30T20:03:25.474673+00:00"
    },
    {
      "district_id": "36",
      "district": "VEHARI",
      "slug": "vehari",
      "file": "data/vehari.json",
      "total_schools": 1101,
      "total_students": 289196,
      "total_boys": 141204,
      "total_girls": 147968,
      "scraped_at": "2026-06-30T20:03:25.474673+00:00"
    },
    {
      "district_id": "40",
      "district": "WAZIRABAD",
      "slug": "wazirabad",
      "file": "data/wazirabad.json",
      "total_schools": 313,
      "total_students": 80918,
      "total_boys": 35500,
      "total_girls": 45414,
      "scraped_at": "2026-06-30T20:03:25.474673+00:00"
    }
  ]
}